pgcachewatch/__init__.py
pgcachewatch/__main__.py
pgcachewatch/_version.py
pgcachewatch/cli.py
pgcachewatch/decorators.py
pgcachewatch/listeners.py
pgcachewatch/logconfig.py
pgcachewatch/models.py
pgcachewatch/pg_event_distributor.py
pgcachewatch/queries.py
pgcachewatch/strategies.py
pgcachewatch/utils.py
PGCacheWatch-0.4.2.dist-info/LICENSE
PGCacheWatch-0.4.2.dist-info/METADATA
PGCacheWatch-0.4.2.dist-info/WHEEL
PGCacheWatch-0.4.2.dist-info/top_level.txt
PGCacheWatch-0.4.2.dist-info/RECORD
