Metadata-Version: 2.1
Name: PGCacheWatch
Version: 0.4.2
Summary: A Python library for real-time PostgreSQL event-driven cache invalidation.
Author: janbjorge
License: Apache 2.0
Project-URL: Documentation, https://github.com/janbjorge/pgcachewatch/
Project-URL: Homepage, https://github.com/janbjorge/pgcachewatch/
Project-URL: Issues, https://github.com/janbjorge/pgcachewatch/issues
Project-URL: Repository, https://github.com/janbjorge/pgcachewatch/
Classifier: Development Status :: 5 - Production/Stable
Classifier: Environment :: Other Environment
Classifier: Environment :: Web Environment
Classifier: Framework :: AsyncIO
Classifier: Intended Audience :: Developers
Classifier: License :: OSI Approved :: Apache Software License
Classifier: Natural Language :: English
Classifier: Operating System :: OS Independent
Classifier: Programming Language :: Python :: 3.10
Classifier: Programming Language :: Python :: 3.11
Classifier: Programming Language :: Python :: 3.12
Classifier: Programming Language :: Python
Classifier: Topic :: Database
Classifier: Topic :: Software Development :: Libraries :: Python Modules
Classifier: Topic :: Utilities
Requires-Python: >=3.10
License-File: LICENSE
Requires-Dist: asyncpg >=0.27.0
Requires-Dist: pydantic >=2.0.0
Requires-Dist: websockets >=12.0.0
Provides-Extra: dev
Requires-Dist: asyncpg-stubs ; extra == 'dev'
Requires-Dist: fastapi ; extra == 'dev'
Requires-Dist: httpx ; extra == 'dev'
Requires-Dist: mypy-extensions ; extra == 'dev'
Requires-Dist: mypy ; extra == 'dev'
Requires-Dist: pytest-asyncio ; extra == 'dev'
Requires-Dist: pytest ; extra == 'dev'
Requires-Dist: ruff ; extra == 'dev'
Requires-Dist: uvicorn ; extra == 'dev'
Provides-Extra: docs
Requires-Dist: myst-parser ; extra == 'docs'
Requires-Dist: sphinx ; extra == 'docs'
Requires-Dist: sphinx-rtd-theme ; extra == 'docs'
